.cproject
.gitignore
.gitmodules
.project
.pydevproject
CHANGELOG
CMakeLists.txt
LICENSE
README.md
TODO.md
_config.yml
contributing.md
notes.md
setup.cfg
setup.py
.github/workflows/build_docs.yml
.github/workflows/build_package.yml
.settings/.gitignore
.settings/org.eclipse.core.resources.prefs
.vscode/c_cpp_properties.json
.vscode/settings.json
baggianalysis.egg-info/PKG-INFO
baggianalysis.egg-info/SOURCES.txt
baggianalysis.egg-info/dependency_links.txt
baggianalysis.egg-info/entry_points.txt
baggianalysis.egg-info/not-zip-safe
baggianalysis.egg-info/top_level.txt
docs/Makefile
docs/_config.yml
docs/conf.py
docs/converters.md
docs/index.md
docs/install.md
docs/requirements.txt
docs/traj.md
docs/utils.md
docs/core/core.md
docs/core/exporters.md
docs/core/filters.md
docs/core/neighbours.md
docs/core/observables.md
docs/core/parsers.md
docs/core/particles.md
docs/core/topology.md
docs/core/trajectories.md
docs/core/utils.md
docs/core/images/pore_size.png
docs/extending/parser.md
docs/extending/topology.md
examples/LAMMPS/analyse.py
examples/LAMMPS/datafile.lammps
examples/oxDNA/patch_to_cogli.py
examples/oxDNA/sq.py
exec/CMakeLists.txt
exec/bop.py
exec/poresize.py
exec/test_feature.cpp
exec/test_feature.py
extern/fast_double_parser/LICENSE
extern/fast_double_parser/fast_double_parser.h
extern/glm/CMakeLists.txt
extern/glm/common.hpp
extern/glm/exponential.hpp
extern/glm/ext.hpp
extern/glm/fwd.hpp
extern/glm/geometric.hpp
extern/glm/glm.hpp
extern/glm/integer.hpp
extern/glm/mat2x2.hpp
extern/glm/mat2x3.hpp
extern/glm/mat2x4.hpp
extern/glm/mat3x2.hpp
extern/glm/mat3x3.hpp
extern/glm/mat3x4.hpp
extern/glm/mat4x2.hpp
extern/glm/mat4x3.hpp
extern/glm/mat4x4.hpp
extern/glm/matrix.hpp
extern/glm/packing.hpp
extern/glm/trigonometric.hpp
extern/glm/vec2.hpp
extern/glm/vec3.hpp
extern/glm/vec4.hpp
extern/glm/vector_relational.hpp
extern/glm/detail/_features.hpp
extern/glm/detail/_fixes.hpp
extern/glm/detail/_noise.hpp
extern/glm/detail/_swizzle.hpp
extern/glm/detail/_swizzle_func.hpp
extern/glm/detail/_vectorize.hpp
extern/glm/detail/compute_common.hpp
extern/glm/detail/compute_vector_relational.hpp
extern/glm/detail/func_common.inl
extern/glm/detail/func_common_simd.inl
