Metadata-Version: 2.1
Name: baggianalysis
Version: 0.6.0
Summary: A C++/Python library to facilitate the analysis of molecular simulations
Home-page: https://github.com/lorenzo-rovigatti/baggianalysis
Author: Lorenzo Rovigatti
Author-email: lorenzo.rovigatti@uniroma1.it
License: GNU GPL 3.0
Classifier: Development Status :: 4 - Beta
Classifier: Environment :: Console
Classifier: Intended Audience :: Science/Research
Classifier: License :: OSI Approved :: GNU General Public License v3 (GPLv3)
Classifier: Operating System :: OS Independent
Classifier: Programming Language :: C++
Classifier: Topic :: Scientific/Engineering :: Physics
License-File: LICENSE
